CHANGES
LICENSE
MANIFEST.in
setup.cfg
setup.py
state_machine_crawler/__init__.py
state_machine_crawler/autodiscover.py
state_machine_crawler/blocks.py
state_machine_crawler/cli.py
state_machine_crawler/collection.py
state_machine_crawler/errors.py
state_machine_crawler/logger.py
state_machine_crawler/state_machine_crawler.py
state_machine_crawler/webview.py
state_machine_crawler.egg-info/PKG-INFO
state_machine_crawler.egg-info/SOURCES.txt
state_machine_crawler.egg-info/dependency_links.txt
state_machine_crawler.egg-info/entry_points.txt
state_machine_crawler.egg-info/requires.txt
state_machine_crawler.egg-info/top_level.txt
state_machine_crawler/serializers/__init__.py
state_machine_crawler/serializers/dot.py
state_machine_crawler/serializers/hierarchy.py
state_machine_crawler/serializers/svg.py
state_machine_crawler/serializers/text.py
state_machine_crawler/webview/index.html
state_machine_crawler/webview/jquery-2.1.3.min.js
tests/__init__.py
tests/cases.py
tests/collection_tests.py
tests/dot_tests.py
tests/function_tests.py
tests/non_tpl_cases.py
tests/solo_tpl_state.py
tests/state_tests.py
tests/tpl_cases.py
tests/utils.py