Metadata-Version: 1.0
Name: state-machine-crawler
Version: 8.5
Summary: A library for following automata based programming model.
Home-page: UNKNOWN
Author: Anton Berezin
Author-email: gurunars@gmail.com
License: UNKNOWN
Platform: UNKNOWN
